{"keyword":"メール","data":[{"name":"多摩職業能力開発センター","province":"東京都","city":"昭島市","address":"東京都昭島市東町3丁目6-33","lat":35.69974508,"lon":139.39149757},{"name":"産業技術研究センター多摩テクノプラザ","province":"東京都","city":"昭島市","address":"東京都昭島市東町3丁目6-1","lat":35.69976454,"lon":139.39225862},{"name":"昭和高等学校","province":"東京都","city":"昭島市","address":"東京都昭島市東町2丁目3-21","lat":35.70384171,"lon":139.38706448},{"name":"拝島高等学校","province":"東京都","city":"昭島市","address":"東京都昭島市拝島町4丁目13-1","lat":35.70386031,"lon":139.34331551},{"name":"多摩職業能力開発センター","province":"東京都","city":"昭島市","address":"東京都昭島市東町3丁目6-33","lat":35.69974508,"lon":139.39149757},{"name":"産業技術研究センター多摩テクノプラザ","province":"東京都","city":"昭島市","address":"東京都昭島市東町3丁目6-1","lat":35.69976454,"lon":139.39225862},{"name":"昭和高等学校","province":"東京都","city":"昭島市","address":"東京都昭島市東町2丁目3-21","lat":35.70384171,"lon":139.38706448},{"name":"拝島高等学校","province":"東京都","city":"昭島市","address":"東京都昭島市拝島町4丁目13-1","lat":35.70386031,"lon":139.34331551},{"name":"多摩職業能力開発センター","province":"東京都","city":"昭島市","address":"東京都昭島市東町3丁目6-33","lat":35.69974508,"lon":139.39149757},{"name":"産業技術研究センター多摩テクノプラザ","province":"東京都","city":"昭島市","address":"東京都昭島市東町3丁目6-1","lat":35.69976454,"lon":139.39225862},{"name":"昭和高等学校","province":"東京都","city":"昭島市","address":"東京都昭島市東町2丁目3-21","lat":35.70384171,"lon":139.38706448},{"name":"拝島高等学校","province":"東京都","city":"昭島市","address":"東京都昭島市拝島町4丁目13-1","lat":35.70386031,"lon":139.34331551},{"name":"多摩職業能力開発センター","province":"東京都","city":"昭島市","address":"東京都昭島市東町3丁目6-33","lat":35.69974508,"lon":139.39149757},{"name":"産業技術研究センター多摩テクノプラザ","province":"東京都","city":"昭島市","address":"東京都昭島市東町3丁目6-1","lat":35.69976454,"lon":139.39225862},{"name":"昭和高等学校","province":"東京都","city":"昭島市","address":"東京都昭島市東町2丁目3-21","lat":35.70384171,"lon":139.38706448},{"name":"拝島高等学校","province":"東京都","city":"昭島市","address":"東京都昭島市拝島町4丁目13-1","lat":35.70386031,"lon":139.34331551},{"name":"多摩職業能力開発センター","province":"東京都","city":"昭島市","address":"東京都昭島市東町3丁目6-33","lat":35.69974508,"lon":139.39149757},{"name":"産業技術研究センター多摩テクノプラザ","province":"東京都","city":"昭島市","address":"東京都昭島市東町3丁目6-1","lat":35.69976454,"lon":139.39225862},{"name":"昭和高等学校","province":"東京都","city":"昭島市","address":"東京都昭島市東町2丁目3-21","lat":35.70384171,"lon":139.38706448},{"name":"拝島高等学校","province":"東京都","city":"昭島市","address":"東京都昭島市拝島町4丁目13-1","lat":35.70386031,"lon":139.34331551},{"name":"多摩職業能力開発センター","province":"東京都","city":"昭島市","address":"東京都昭島市東町3丁目6-33","lat":35.69974508,"lon":139.39149757},{"name":"産業技術研究センター多摩テクノプラザ","province":"東京都","city":"昭島市","address":"東京都昭島市東町3丁目6-1","lat":35.69976454,"lon":139.39225862},{"name":"昭和高等学校","province":"東京都","city":"昭島市","address":"東京都昭島市東町2丁目3-21","lat":35.70384171,"lon":139.38706448},{"name":"拝島高等学校","province":"東京都","city":"昭島市","address":"東京都昭島市拝島町4丁目13-1","lat":35.70386031,"lon":139.34331551},{"name":"多摩職業能力開発センター","province":"東京都","city":"昭島市","address":"東京都昭島市東町3丁目6-33","lat":35.69974508,"lon":139.39149757},{"name":"産業技術研究センター多摩テクノプラザ","province":"東京都","city":"昭島市","address":"東京都昭島市東町3丁目6-1","lat":35.69976454,"lon":139.39225862},{"name":"昭和高等学校","province":"東京都","city":"昭島市","address":"東京都昭島市東町2丁目3-21","lat":35.70384171,"lon":139.38706448},{"name":"拝島高等学校","province":"東京都","city":"昭島市","address":"東京都昭島市拝島町4丁目13-1","lat":35.70386031,"lon":139.34331551}]}