{"keyword":"管","data":[{"name":"大島のサクラ株","province":"東京都","city":"大島町","address":"東京都大島町泉津","lat":34.78307496,"lon":139.41375561},{"name":"カモシカ","province":"東京都","city":"大島町","address":"東京都大島町泉津","lat":34.78307496,"lon":139.41375561},{"name":"シイノキ山のシイノキ群叢","province":"東京都","city":"大島町","address":"東京都大島町泉津","lat":34.78307496,"lon":139.41375561},{"name":"大島海浜植物群落","province":"東京都","city":"大島町","address":"東京都大島町泉津","lat":34.78307496,"lon":139.41375561},{"name":"オジロワシ","province":"東京都","city":"大島町","address":"東京都大島町泉津","lat":34.78307496,"lon":139.41375561},{"name":"コクガン","province":"東京都","city":"大島町","address":"東京都大島町泉津","lat":34.78307496,"lon":139.41375561},{"name":"マガン","province":"東京都","city":"大島町","address":"東京都大島町泉津","lat":34.78307496,"lon":139.41375561},{"name":"鉄砲場の岩陰遺跡","province":"東京都","city":"大島町","address":"東京都大島町泉津","lat":34.78307496,"lon":139.41375561},{"name":"大島下高洞遺跡","province":"東京都","city":"大島町","address":"東京都大島町元町","lat":34.75069975,"lon":139.35458395},{"name":"大島竜の口遺跡","province":"東京都","city":"大島町","address":"東京都大島町野増","lat":34.73029943,"lon":139.35466575},{"name":"役行者窟","province":"東京都","city":"大島町","address":"東京都大島町泉津","lat":34.78307496,"lon":139.41375561},{"name":"秋広平六墓","province":"東京都","city":"大島町","address":"東京都大島町波浮港","lat":34.68677239,"lon":139.44189881},{"name":"差木地の大クス","province":"東京都","city":"大島町","address":"東京都大島町差木地","lat":34.68312246,"lon":139.41394612},{"name":"潮吹の鼻","province":"東京都","city":"大島町","address":"東京都大島町泉津","lat":34.78307496,"lon":139.41375561},{"name":"おたいね浦の岩脈と筆島","province":"東京都","city":"大島町","address":"東京都大島町波浮港","lat":34.68677239,"lon":139.44189881},{"name":"野増大宮神社の十二座神楽","province":"東京都","city":"大島町","address":"東京都大島町野増大宮上手（字）","lat":34.73296069,"lon":139.37116714},{"name":"カラスバト","province":"東京都","city":"大島町","address":"東京都大島町泉津","lat":34.78307496,"lon":139.41375561},{"name":"元町のハマンカー（南井戸）","province":"東京都","city":"大島町","address":"東京都大島町元町","lat":34.75069975,"lon":139.35458395},{"name":"赤穂義士　間瀬定八の墓","province":"東京都","city":"大島町","address":"東京都大島町元町","lat":34.75069975,"lon":139.35458395},{"name":"力士　大島伝吉の碑（勇鑑石とも）","province":"東京都","city":"大島町","address":"東京都大島町岡田","lat":34.78878237,"lon":139.39285739},{"name":"粟本佐次朗記念碑（テリコの碑）","province":"東京都","city":"大島町","address":"東京都大島町岡田","lat":34.78878237,"lon":139.39285739},{"name":"波浮港開港碑","province":"東京都","city":"大島町","address":"東京都大島町波浮港","lat":34.68677239,"lon":139.44189881}]}